{
  "Main": {
    "name": {
      "type": "Text",
      "config": {
        "label": "Name"
      }
    },
    "uid": {
      "type": "UID",
      "config": {
        "label": "Slug"
      }
    },
    "category": {
      "type": "Link",
      "config": {
        "select": "document",
        "customtypes": ["category"],
        "label": "Category"
      }
    },
    "price": {
      "type": "Number",
      "config": {
        "label": "Price"
      }
    },
    "colors": {
      "type": "Group",
      "config": {
        "fields": {
          "image": {
            "type": "Image",
            "config": {
              "constraint": {
                "width": 1080,
                "height": 1080
              },
              "thumbnails": [],
              "label": "Image"
            }
          },
          "color": {
            "type": "Select",
            "config": {
              "options": [
                "AQUAMARINE",
                "BLACK",
                "BURGUNDY",
                "CHARCOAL_GREY",
                "FADED_DENIM",
                "LIGHT_CHARCOAL",
                "MELANGE_GREY",
                "NAVY",
                "WHITE"
              ],
              "label": "Color"
            }
          }
        },
        "label": "Colors"
      }
    },
    "sizes": {
      "type": "Group",
      "config": {
        "fields": {
          "size": {
            "type": "Select",
            "config": {
              "options": [
                "XS",
                "S",
                "M",
                "L",
                "XL",
                "XXL",
                "YEARS_3_4",
                "MONTHS_0_3",
                "MONTHS_3_6"
              ],
              "label": "Size"
            }
          }
        },
        "label": "Sizes"
      }
    }
  }
}
